LICENSE
MANIFEST.in
README.rst
setup.py
unichain/__init__.py
unichain/core.py
unichain/helpers.py
unichain.egg-info/PKG-INFO
unichain.egg-info/SOURCES.txt
unichain.egg-info/dependency_links.txt
unichain.egg-info/top_level.txt