Metadata-Version: 2.1
Name: unichain
Version: 0.1.0
Summary: Unichain SDK by Python
Home-page: https://github.com/uniworld-io/unichain-py
Author: Real Elon Musk
Author-email: realelonmusk102@gmail.com
License: Copyright (c) 2021 UniWorld
Platform: UNKNOWN
License-File: LICENSE
